django_usda_nutrition-0.0.2.dist-info/DESCRIPTION.rst
django_usda_nutrition-0.0.2.dist-info/METADATA
django_usda_nutrition-0.0.2.dist-info/metadata.json
django_usda_nutrition-0.0.2.dist-info/RECORD
django_usda_nutrition-0.0.2.dist-info/top_level.txt
django_usda_nutrition-0.0.2.dist-info/WHEEL
usda_nutrition/__init__.py
usda_nutrition/models.py
usda_nutrition/data/sr28/DATA_SRC.txt
usda_nutrition/data/sr28/DATSRCLN.txt
usda_nutrition/data/sr28/DERIV_CD.txt
usda_nutrition/data/sr28/FD_GROUP.txt
usda_nutrition/data/sr28/FOOD_DES.txt
usda_nutrition/data/sr28/FOOTNOTE.txt
usda_nutrition/data/sr28/LANGDESC.txt
usda_nutrition/data/sr28/LANGUAL.txt
usda_nutrition/data/sr28/NUT_DATA.txt
usda_nutrition/data/sr28/NUTR_DEF.txt
usda_nutrition/data/sr28/SRC_CD.txt
usda_nutrition/data/sr28/WEIGHT.txt
usda_nutrition/management/__init__.py
usda_nutrition/management/commands/__init__.py
usda_nutrition/management/commands/import_db.py
usda_nutrition/management/commands/import_usda.py
