Metadata-Version: 2.0
Name: django-usda-nutrition
Version: 0.0.2
Summary: Django application for working with the USDA nutrition database.
Home-page: https://github.com/danielnaab/django-usda-nutrition
Author: Daniel Naab
Author-email: dan@crushingpennies.com
License: BSD
Keywords: django
Platform: UNKNOWN
Classifier: Development Status :: 3 - Alpha
Classifier: License :: OSI Approved :: BSD License
Classifier: Intended Audience :: Developers
Classifier: Programming Language :: Python
Classifier: Programming Language :: Python :: 2
Classifier: Programming Language :: Python :: 3
Classifier: Framework :: Django
Classifier: Framework :: Django :: 1.9
